{
    "title": "有馬記念の後に・来",
    "no_wrap": true,
    "text_block_list": [
        {
            "name": "Monologue",
            "text": "Narita Brian finishes first at the Arima Kinen.\nHowever, she and Biwa Hayahide are both aiming\nto achieve even greater goals."
        },
        {
            "name": "Monologue",
            "text": "From the stands, Symboli Rudolf's heart leaps\nwith quiet excitement. She too wants to face\nNarita Brian someday..."
        },
        {
            "name": "Monologue",
            "text": "Those who have been defeated are aiming for the\ntop, just the same as Narita Brian. They will\nalways continue to be her competitors."
        },
        {
            "name": "Monologue",
            "text": "And so, the curtain falls on the Arima Kinen.\nNarita Brian will continue to run from here on out\nin her never-ending search for stronger\nopponents."
        }
    ]
}