{
    "title": "追想のインスピレーション",
    "no_wrap": true,
    "text_block_list": [
        {
            "name": "Monologue",
            "text": "It's been some time since I became Satono Diamond's official trainer,\nbut each day comes with new surprises."
        },
        {
            "name": "Satono Diamond",
            "text": "Trainer! I'm appointing you vice director of the School-Wide Floral\nMakeover Project!",
            "choice_data_list": [
                "Come again?"
            ]
        },
        {
            "name": "Satono Diamond",
            "text": "Oh, you're not familiar? Um, the School-Wide Floral Makeover\nProject is..."
        },
        {
            "name": "Satono Diamond",
            "text": "As its name suggests, an annual event where volunteers decorate the\nwhole school with flowers!"
        },
        {
            "name": "Satono Diamond",
            "text": "And <i>I'm</i> directing the project this year! ♪ It's a big responsibility!"
        },
        {
            "name": "Satono Diamond",
            "text": "To guarantee success, I'll need a vice director with a cool head and\neye for detail—that's you, Trainer! I can think of no one better!",
            "choice_data_list": [
                "Happy to help."
            ]
        },
        {
            "name": "Satono Diamond",
            "text": "Aha! Thank you! Let's brighten up the school and put a smile on\neveryone's faces!"
        },
        {
            "name": "Satono Diamond",
            "text": "We'll hang colorful baskets everywhere, and make a whole mini\necosystem out of the courtyard... Oh, there are so many options!",
            "choice_data_list": [
                "Dreaming big, huh?",
                "Dreaming big, huh?"
            ]
        },
        {
            "name": "Satono Diamond",
            "text": "Oh, you think? I was just picturing the western-style garden my family\nowns..."
        },
        {
            "name": "Satono Diamond",
            "text": "But now that you mention it, we might not have the manpower. Hmm...\nWhat's something else we could try?",
            "choice_data_list": [
                "Let's scope the school out for ideas.",
                "Let's scope the school out for ideas."
            ]
        },
        {
            "name": "Satono Diamond",
            "text": "I've already seen so many places that could use some floral\ndecorating. Let's check the school building next!"
        },
        {
            "name": "Satono Diamond",
            "text": "Oh! I'm sorry, we didn't know someone was already here."
        },
        {
            "name": "Student A",
            "text": "Um... <i>sniff.</i> I-it's okay. <i>Hic!</i> Excuse me!"
        },
        {
            "name": "Satono Diamond",
            "text": "She left...",
            "choice_data_list": [
                "What was she doing here?"
            ]
        },
        {
            "name": "Satono Diamond",
            "text": "A lot of students come here when things get tough. Some alone time\ncan help sort out your feelings."
        },
        {
            "name": "Satono Diamond",
            "text": "I know! If there were some flowers..."
        },
        {
            "name": "Satono Diamond",
            "text": "What do you think, Vice Director?! We could put a planter here!"
        },
        {
            "name": "Satono Diamond",
            "text": "Flowers are soothing for the heart, no matter how down you're\nfeeling. They're sure to cheer the students up!",
            "choice_data_list": [
                "That's a great idea!",
                "That's a great idea!"
            ]
        },
        {
            "name": "Satono Diamond",
            "text": "Isn't it just? It's genius, if I say so myself. Hehe, you know, this really\ntakes me back.",
            "choice_data_list": [
                "It does?"
            ]
        },
        {
            "name": "Satono Diamond",
            "text": "Yes. Do you remember when my parents and McQueen gave us their\napproval?"
        },
        {
            "name": "Satono Diamond",
            "text": "Our number one goal... is achieving our dream. Not passing today's\ntrial."
        },
        {
            "name": "Satono Diamond",
            "text": "So we only trained the qualities I need right now. Even if you might\nnot like it..."
        },
        {
            "name": "Satono Diamond",
            "text": "Just like back then, what we need right now isn't to pretty up the\nschool..."
        },
        {
            "name": "Satono Diamond",
            "text": "It's to brighten everyone's day! Once again, you've helped me realize\nwhat's important."
        },
        {
            "name": "Satono Diamond",
            "text": "Vice Director! Let's prepare our presentation right away! With our\nteamwork, I just know we'll create a plan that will knock everyone's\nsocks off!"
        },
        {
            "name": "Monologue",
            "text": "We spend the rest of the day working, barely finishing in time for\ncurfew. The next day..."
        },
        {
            "name": "Satono Diamond",
            "text": "...And that's our proposal for this year's project! What do you think,\neveryone?"
        },
        {
            "name": "Upperclassman A",
            "text": "I'm for it! I think it's great!"
        },
        {
            "name": "Upperclassman B",
            "text": "Yeah! Great job, Dia! I can't believe you put all of this together by\nyourself!"
        },
        {
            "name": "Satono Diamond",
            "text": "Oh, no, this wasn't all me—I couldn't have done it without my trainer's\nhelp!"
        },
        {
            "name": "Satono Diamond",
            "text": "We worked in the library until late last night. I couldn't have asked for\na better assistant!"
        },
        {
            "name": "Upperclassman B",
            "text": "No wonder! I'm impressed you can be so open and, like... proactive! I\nalways feel bad asking adults for help."
        },
        {
            "name": "Satono Diamond",
            "text": "...You think so?"
        },
        {
            "name": "Monologue",
            "text": "The older student's words don't quite seem to click for Satono\nDiamond. Her earnest nature ensures she never hesitates to ask for\nhelp—or give it in turn."
        }
    ]
}