{
    "title": "0",
    "no_wrap": true,
    "text_block_list": [
        {
            "name": "Kitasan Black",
            "text": "C.B., you got a special feature... Oh! And so did\nTeio! Ooh! I'm gonna keep this thing forever!"
        },
        {
            "name": "Mr. C.B.",
            "text": "Come to think of it, you look up to Teio, right?\nRudolf mentioned it to me."
        },
        {
            "name": "Kitasan Black",
            "text": "You bet I do! The powerful confidence she runs\nwith comes through, even in these photos."
        },
        {
            "name": "Kitasan Black",
            "text": "When I look at them, all I can think about is how I\nwanna reach her level one day!"
        },
        {
            "name": "Kitasan Black",
            "text": "Even if I can't catch up right now, I'll keep running\nfor as long as it takes, until we're shoulder to\nshoulder!"
        },
        {
            "name": "Mr. C.B.",
            "text": "Yeah? Then you'll probably make it into a special\nfeature too, before long."
        },
        {
            "name": "Kitasan Black",
            "text": "Huh?! Y-you think so?! ...Does that mean I might\nget to be interviewed alongside Teio?!"
        },
        {
            "name": "Kitasan Black",
            "text": "Oh, C.B.! What was it like being photographed\nwith Rudolf and so many other famous\nUmamusume?!"
        },
        {
            "name": "Mr. C.B.",
            "text": "Hmm... Good question. Heh, I can't say I really\nremember. Guess it wasn't that special to me."
        },
        {
            "name": "Kitasan Black",
            "text": "W-wow! I should've guessed! If it were me, I'd be\nso nervous my face would lock up!"
        },
        {
            "name": "Mr. C.B.",
            "text": "Yeah? Well, while I don't really remember how I\nfelt... things like this <i>are</i> fun to think about."
        },
        {
            "name": "Mr. C.B.",
            "text": "The time forgotten by me remains in the hands of\nothers... Yeah. That's a fun thought."
        }
    ]
}