{
    "title": "孤島の女王",
    "no_wrap": true,
    "text_block_list": [
        {
            "name": "Monologue",
            "text": "On a deserted island somewhere in the middle of\nthe ocean...\nA ship drops off a dumbfounded Mejiro McQueen\nand quickly departs."
        },
        {
            "name": "Mejiro McQueen",
            "text": "What is the meaning of this? What could they\npossibly mean by \"survive the night?\""
        },
        {
            "name": "Mejiro McQueen",
            "text": "Do you know anything about this, Trainer?",
            "choice_data_list": [
                "It's a project for the school newspaper."
            ]
        },
        {
            "name": "Monologue",
            "text": "I tell her everything I know—that this is for an\narticle called \"Deserted Island: How Will the\nPampered Survive?\""
        },
        {
            "name": "Mejiro McQueen",
            "text": "I see. So they want a sheltered person like me to\ntry and overcome the dangers of a place like this."
        },
        {
            "name": "Mejiro McQueen",
            "text": "Then I will gladly accept the challenge! I won't be\nintimidated by the likes of this island!"
        },
        {
            "name": "Mejiro McQueen",
            "text": "Th-that said, it is a rather unsettling place. The\nthought of having to spend an entire night here\nis..."
        },
        {
            "name": "Mejiro McQueen",
            "text": "Aaaah! Is that a tiger?! A Bengal tiger?!"
        },
        {
            "name": "Mejiro McQueen",
            "text": "I will not be bested!"
        },
        {
            "name": "Mejiro McQueen",
            "text": "First things first. We must come up with a plan. I'll\nneed your assistance, Trainer!"
        },
        {
            "name": "Mejiro McQueen",
            "text": "What is the most important thing for surviving on\na deserted island? Come, let's hear your answer."
        },
        {
            "name": "Monologue",
            "text": "The most essential thing for survival is...",
            "choice_data_list": [
                "Food.",
                "Endurance."
            ]
        },
        {
            "name": "Mejiro McQueen",
            "text": "Food... You're saying that as long as we have\nnourishment, there's nothing to fear?"
        },
        {
            "name": "Mejiro McQueen",
            "text": "You're right. I'll never get home if all I do is sit\nhere and dread the worst. It's time I start fending\nfor myself!"
        },
        {
            "name": "Mejiro McQueen",
            "text": "Now then, Trainer, whenever you're ready.",
            "choice_data_list": [
                "Huh?"
            ]
        },
        {
            "name": "Mejiro McQueen",
            "text": "Why, the food! You're going to bring us some,\naren't you? I promise, I'll eat anything necessary\nto survive!"
        },
        {
            "name": "Mejiro McQueen",
            "text": "I won't be picky, be it fruit or seafood. Now, get\nto it!"
        },
        {
            "name": "Monologue",
            "text": "And so Mejiro McQueen is able to secure food\nwithout so much as lifting a finger."
        },
        {
            "name": "Mejiro McQueen",
            "text": "Endurance... I see. Without inexhaustible\nendurance, getting home safe is nothing but a\nfantasy."
        },
        {
            "name": "Mejiro McQueen",
            "text": "I suppose that means I will have to best that tiger\nin order to get stronger..."
        },
        {
            "name": "Mejiro McQueen",
            "text": "Eeeeek! Is it still lurking in the bush?! I don't think\nI can do this after all!"
        },
        {
            "name": "Mejiro McQueen",
            "text": "I don't think this endurance idea will work out,\nTrainer... I couldn't possibly—aaah!"
        },
        {
            "name": "Monologue",
            "text": "The beast chases Mejiro McQueen around and\naround. I can't help but think that this may just be\nhelping to improve her endurance."
        }
    ]
}