{
    "title": "クレーンゲームに挑戦！",
    "no_wrap": true,
    "text_block_list": [
        {
            "name": "モノローグ",
            "text": "ある日、\nシーキングザパールと出かけた先で――"
        },
        {
            "name": "シーキングザパール",
            "text": "――あら。"
        },
        {
            "name": "モノローグ",
            "text": "シーキングザパールの視線の先には、\nウマ娘たちをモチーフにしたぬいぐるみが\n入った、クレーンゲームがあった。"
        },
        {
            "name": "シーキングザパール",
            "text": "クラスメイトが言っていたわ。\nここの『ぱかプチ』はゲットが大変だって。"
        },
        {
            "name": "シーキングザパール",
            "text": "フフッ、面白いじゃない。\nレッツ・トライ！"
        },
        {
            "name": "シーキングザパール",
            "text": "くぅっ……！　ノーグッド……！"
        },
        {
            "name": "シーキングザパール",
            "text": "簡単にはゲットできない……\nだからこそエキサイトするのね……。",
            "choice_data_list": [
                "俺が可能性を示そう",
                "私が可能性を示すね"
            ]
        },
        {
            "name": "シーキングザパール",
            "text": "！　フッ……面白いことを言ってくれるわね。\nいいわ――"
        },
        {
            "name": "シーキングザパール",
            "text": "選手交代よ！\n貴方の可能性、見せてちょうだい！"
        },
        {
            "name": "モノローグ",
            "text": "――このゲーム、負けられない！！"
        }
    ]
}