{
    "title": "私のファーストライブ",
    "no_wrap": true,
    "text_block_list": [
        {
            "text": "来たるスマートファルコンの誕生日ライブ。\nそこでファンにプレゼントする特別映像を、\n2人で確認することになった。"
        },
        {
            "name": "スマートファルコン",
            "text": "『わ～！　限定ケーキかわいいっ♪\nさすがウマ娘が選ぶスイーツ100名店☆』"
        },
        {
            "name": "スマートファルコン",
            "text": "『まあ、これは？　トレンド調査の一環だし？\nランチ前に食べてもいいよね～☆\n……あっ、ウマスタ用の写真も撮っちゃお♪』"
        },
        {
            "name": "スマートファルコン",
            "text": "『……あれ？　スマホ、どこ？\nちゃんとカバン入れたはずなのに！\nふえ～～ん！　どこいっちゃったの～！？』"
        },
        {
            "text": "スマートファルコンの日常を切り取った\nレアな映像になっている。\n整理整頓が苦手なのもご愛敬だ。",
            "choice_data_list": [
                "うん、いい感じじゃないかな！"
            ]
        },
        {
            "name": "スマートファルコン",
            "text": "確かにそうなんだけど……\nう～～～ん……。",
            "choice_data_list": [
                "納得いかない？"
            ]
        },
        {
            "name": "スマートファルコン",
            "text": "これだといつもと変わらないよね？\nせっかくの誕生日ライブなのに、\nスペシャル感が足りないと思うんだ。"
        },
        {
            "name": "スマートファルコン",
            "text": "もっと深くファル子を知ってほしい！\nそれで、ファンのみんなとの距離を\nグーンと縮めたいの！"
        },
        {
            "text": "今まで見せたことのない姿を見せたい。\nとなれば、彼女のことを深く知っている\n人物に協力を仰ぐのがよさそうだ。",
            "choice_data_list": [
                "ご両親に相談してみたら？"
            ]
        },
        {
            "name": "スマートファルコン",
            "text": "それいいかも♪\nちょっと聞いてみるね！"
        },
        {
            "text": "そしてスマートファルコンが\nご両親に相談したところ、\nすぐに返事が送られてきた。"
        },
        {
            "name": "スマートファルコン",
            "text": "あっ……動画が添付してある！　なんだろ？\n一緒に見てみよ、トレーナーさん！"
        },
        {
            "name": "スマートファルコン",
            "text": "……家族でクリスマスパーティーした時の\n動画かな？　あれ、じゃあこの小さい子は――"
        },
        {
            "name": "幼いファルコン",
            "text": "『いっぱい、いっぱい～♪\nきみにあげるね～♪　Chuッ☆』"
        },
        {
            "name": "ファルコンの母親",
            "text": "『きゃー♪　かわいい～！\nアンコール、アンコール☆』"
        },
        {
            "name": "幼いファルコン",
            "text": "『えへへ♪　ちゅっ、ちゅっ、ちゅっ☆』"
        },
        {
            "text": "小さいスマートファルコンが、\nカメラに向かって投げキッスを繰り返す。\n何度も何度も――",
            "choice_data_list": [
                "か、かわいい……！"
            ]
        },
        {
            "name": "スマートファルコン",
            "text": "きゃあああっ！　止めて止めて～！\n――なにこれ！！\nお父さん、こんな動画持ってたの！？"
        },
        {
            "name": "スマートファルコン",
            "text": "……た、確かにみんなに見せてない\nお宝映像だけどぉ……うぅ……。",
            "choice_data_list": [
                "すごく可愛かったぞ！",
                "すごく可愛かったよ！"
            ]
        },
        {
            "name": "スマートファルコン",
            "text": "あ～ん、やめて～！！\nは……恥ずかしいからぁ……！"
        },
        {
            "name": "スマートファルコン",
            "text": "ふぅ……あれ？\nまた動画が来てる。メッセージも……？"
        },
        {
            "name": "ファルコンの父親",
            "text": "『動画はどうだった？　よく撮れてるだろ？\nあの頃のアイドルごっこの映像なら、\nまだたくさん残っているからな』"
        },
        {
            "name": "ファルコンの父親",
            "text": "『私と母さんが褒めると、目を輝かせて\n何度も披露してくれたんだよ。懐かしいな』"
        },
        {
            "name": "スマートファルコン",
            "text": "ふふふっ、そうだっけ……。"
        },
        {
            "name": "ファルコンの父親",
            "text": "『で、今送ったのが外で歌いはじめて\nお買い物ができなかった時の映像だ。\nはっはっは、あの時は困り果てたな～！』"
        },
        {
            "name": "スマートファルコン",
            "text": "えー、私そんなことしてたかなぁ？\n……してたかも。ふふっ！"
        },
        {
            "name": "スマートファルコン",
            "text": "……私が歌うとね、お父さんとお母さんが\n喜んでくれて。その顔が大好きだった。"
        },
        {
            "name": "スマートファルコン",
            "text": "ううん、2人だけじゃない。商店街の人とか、\n友だちとか、みんなの喜ぶ顔が！"
        },
        {
            "name": "スマートファルコン",
            "text": "……この小さなライブが、私のはじまり。\n私の夢のスタート――"
        },
        {
            "name": "スマートファルコン",
            "text": "うん！　ちょっと恥ずかしいけど、\nこの動画、今度の誕生日ライブで流そう！"
        },
        {
            "name": "スマートファルコン",
            "text": "私の夢のはじまりを、\nみんなにも知ってもらいたいもん！"
        },
        {
            "name": "スマートファルコン",
            "text": "……そうだ！　動画で歌ってた曲も、\nステージで歌おっかな☆"
        },
        {
            "name": "スマートファルコン",
            "text": "ファル子、こんなに成長したよ～♪\nって、みんなに見てもらうんだ☆"
        },
        {
            "text": "子どものようにはしゃぎながら、\nレッスンへ向かうスマートファルコンだった！"
        },
        {
            "name": "スマートファルコン",
            "text": "あれ、またお父さんからだ！\n『他にももっと秘蔵の動画が\nあるけど、いる？』……だって。"
        },
        {
            "name": "スマートファルコン",
            "text": "うーん、あんまり増えると特別感ないよね？\n残りはまた今度のお楽しみ、ってことで♪"
        },
        {
            "text": "いつか、さらなるお宝映像が\n解禁される日を楽しみにしつつ、\n誕生日ライブの準備を進めるのだった！"
        }
    ]
}