{
    "title": "いまのもの",
    "no_wrap": true,
    "text_block_list": [
        {
            "name": "？？？",
            "text": "――我、此処に在り。我等、此処に輝けり。\n幾星霜、定めの果て、数多の縁撚りて集いけり。"
        },
        {
            "name": "？？？",
            "text": "いざやいざや。\n焔よ皆よ、三柱よ。"
        },
        {
            "name": "？？？",
            "text": "今宵、耳立て御覧じろ。"
        },
        {
            "name": "？？？",
            "text": "神馬駆。\n此方より、彼方まで――"
        },
        {
            "name": "モノローグ",
            "text": "イベントタイトルロゴ表示。"
        },
        {
            "name": "ウマ娘A",
            "text": "――ねえねえ、聞いた？　今年の『駿大祭』は久しぶりに\n『神馬駆』やるんだって！"
        },
        {
            "name": "ウマ娘B",
            "text": "『神馬駆』ってあれだよね。レースを引退したウマ娘の想いを\n『蹄板』に書いて焚き上げるイベントみたいな――"
        },
        {
            "name": "ウマ娘C",
            "text": "――なんかウワサだとさ～、今回はトレセン学園から\nその『神馬駆』をやる『神馬』役が選ばれるんだって～。"
        },
        {
            "name": "ウマ娘D",
            "text": "マジ？　『神馬』ってめちゃくちゃ縁起がいいんじゃなかった？\nいいな～。アタシもレースあるからゲン担ぎしたーい！"
        },
        {
            "name": "秋川理事長",
            "text": "――感謝ッ！\n皆それぞれ忙しい中、よくぞ集まってくれた！"
        },
        {
            "name": "タマモクロス",
            "text": "理事長がこうやって呼び出すなんて珍しいですね。\nしかも面子が、なんや顔見知りばっかりやし――"
        },
        {
            "name": "イナリワン",
            "text": "ま、その分話もいろいろと早そうじゃあねえか。\n――それで、どういった用件なんですかい？"
        },
        {
            "name": "秋川理事長",
            "text": "開示ッ！　すでに耳に入っているかもしれないが、今年の\n『駿大祭』では、数年ぶりに『神馬駆』が行われることになった！"
        },
        {
            "name": "メジロアルダン",
            "text": "――三女神の御前で、過去のウマ娘たちの想いを称え慰める、\nウマ娘の、ウマ娘による、ウマ娘のための神事……ですよね。"
        },
        {
            "name": "秋川理事長",
            "text": "肯定ッ！　『想撚』と『想駆』！　2つの儀式で構成される、\nダイナミックかつ神秘的な、由緒正しき神事だ！"
        },
        {
            "name": "秋川理事長",
            "text": "今回、その『神馬駆』の担い手である『神馬』役に――"
        },
        {
            "name": "秋川理事長",
            "text": "――タマモクロス！　オグリキャップ！"
        },
        {
            "name": "秋川理事長",
            "text": "イナリワン！　メジロアルダン！　ヤエノムテキ！\n君たち5名が選ばれた！　祝賀ッ！"
        },
        {
            "name": "ヤエノムテキ",
            "text": "なんと……！\nかの由緒正しき大役に、私たちが……！？"
        },
        {
            "name": "メジロアルダン",
            "text": "身に余る光栄です。トレセン学園のウマ娘から\n『神馬』が選出されるという噂は、本当だったのですね。"
        },
        {
            "name": "秋川理事長",
            "text": "なお、君たち5名には近いうちに、\n『神馬駆』の練習合宿に行ってもらうことになる！"
        },
        {
            "name": "秋川理事長",
            "text": "応援ッ！　君たちにはどうか、トレセン学園の――\nひいては、今を走るウマ娘の代表として務めに邁進してほしい！"
        },
        {
            "name": "タマモクロス",
            "text": "――うーむ。『神馬駆』って確か山の上のほうでやるはずやから、\n虫よけスプレーとかも買うといたほうがええんやろか……？"
        },
        {
            "name": "イナリワン",
            "text": "それなら夏合宿で使ってるヤツを持っていこうぜ。\n……ってオグリよ、どうしたんだい？　菓子をそんな睨んで。"
        },
        {
            "name": "オグリキャップ",
            "text": "いや、おやつはいくらまでならいいかと考えていて。"
        },
        {
            "name": "タマモクロス",
            "text": "遠足かッ！　ったく――"
        },
        {
            "name": "タマモクロス",
            "text": "にしても、選ばれたんが顔見知りばっかなんには驚いたなぁ。\nあれ確か、占いみたいなんで決めてんのやろ？　確率やばないか？"
        },
        {
            "name": "オグリキャップ",
            "text": "私はみんなが一緒で嬉しい。『神馬』がどんなことをするか\nよくわからないけど、選ばれたからには私はその役を全うしたい。"
        },
        {
            "name": "オグリキャップ",
            "text": "タマやみんなとだったら、きっと何とかなる気がする。\nだからみんなと一緒に選ばれて、心強いし、嬉しい。"
        },
        {
            "name": "イナリワン",
            "text": "だっはっはっは！　素直な物言いだねえオグリは！\n大役に選ばれてもいつも通りのツラだしよ！"
        },
        {
            "name": "タマモクロス",
            "text": "ホンマ、アンタは毎度……\n――まあでも、心強いっちゅうんは、同意したるわ。"
        },
        {
            "name": "タマモクロス",
            "text": "縁起がええっちゅうことで、ウチも『神馬』に興味あったからな。\nやるからには、ウチらで過去最高のもんにしたるわ！"
        },
        {
            "name": "オグリキャップ",
            "text": "しかし、合宿か。\n…………ご飯が美味しい所だといいな。"
        },
        {
            "name": "タマモクロス",
            "text": "旅行かッ！"
        },
        {
            "name": "メジロアルダン",
            "text": "……おばあ様は、なんと？"
        },
        {
            "name": "ヤエノムテキ",
            "text": "『務めを立派に果たすように』と仰ってくれたようです。\n……改めて気が引き締まります。"
        },
        {
            "name": "メジロアルダン",
            "text": "……ふふっ。気が引き締まる以上に、とても喜んでいるように\nお見受けします。……尻尾が、少し高く上がっていらしたので。"
        },
        {
            "name": "ヤエノムテキ",
            "text": "それはっ……その……お恥ずかしい限りですが、大役を頂けて\n光栄であると同時に、またとない機会だという心持ちが強く――"
        },
        {
            "name": "ヤエノムテキ",
            "text": "ウマ娘として、金剛八重垣流に名を連ねる者として、\n祖父母に誇らしき姿を見せられれば何よりの幸いと思っています。"
        },
        {
            "name": "ヤエノムテキ",
            "text": "……ところで、そういうアルダンさんこそ、\n嬉しさを感じておられるようにお見受けしますが。"
        },
        {
            "name": "メジロアルダン",
            "text": "ふふっ。実は私も、光栄に思うと同時に楽しみなのです。\nみなさんと共に練習合宿に臨むということが。"
        },
        {
            "name": "メジロアルダン",
            "text": "よい合宿にして、歴史に残る『神馬駆』ができるよう、\n精いっぱい努めましょう。"
        },
        {
            "name": "ヤエノムテキ",
            "text": "ええ、必ず。"
        }
    ]
}