{
    "title": "0",
    "no_wrap": true,
    "text_block_list": [
        {
            "name": "Special Week",
            "text": "There are so many Umamusume here... It still feels\nweird to me."
        },
        {
            "name": "Silence Suzuka",
            "text": "You were the only Umamusume living in your\nhometown, right?"
        },
        {
            "name": "Special Week",
            "text": "Right. That's probably why I get a little nervous\naround the others occasionally..."
        },
        {
            "name": "Special Week",
            "text": "But I made a promise to my mom, so I've gotta\nmake lots and lots of friends here!"
        },
        {
            "name": "Silence Suzuka",
            "text": "Hehe, I'm sure you'll do just that."
        },
        {
            "name": "Special Week",
            "text": "Once I make a hundred friends, I wanna have a\nhuuuge picnic with everyone! ♪"
        },
        {
            "name": "Special Week",
            "text": "When that happens, let's eat lots and lots of\ncarrot sandwiches!"
        },
        {
            "name": "Silence Suzuka",
            "text": "Okay, I can't wait."
        }
    ]
}