{
    "title": "0",
    "no_wrap": true,
    "text_block_list": [
        {
            "name": "Hokko Tarumae",
            "text": "Mmm, delicious! ♪"
        },
        {
            "name": "Hokko Tarumae",
            "text": "...Oops, I mean—mmm, that's <i>mighty</i> tasty! ♪"
        },
        {
            "name": "Copano Rickey",
            "text": "Oh, are you practicing your local idol reactions?"
        },
        {
            "name": "Hokko Tarumae",
            "text": "Yup, I need to work on it every day so it comes\nout naturally!"
        },
        {
            "name": "Copano Rickey",
            "text": "Really? I think it's okay to just act like you\nnormally do."
        },
        {
            "name": "Hokko Tarumae",
            "text": "Not good enough. I need to make this a habit so\nit comes out without thinking, at a moment's\nnotice!"
        },
        {
            "name": "Copano Rickey",
            "text": "Oh, making good habits never hurts. ☆ If your\nhabits change, so does your behavior. And if you\nchange your behavior, you can change your\ndestiny..."
        },
        {
            "name": "Copano Rickey",
            "text": "So the first thing to changing your habits is to\nchange your surroundings. That's the way of feng\nshui!"
        },
        {
            "name": "Hokko Tarumae",
            "text": "Hey, do you have to bring every single thing back\nto feng shui?"
        },
        {
            "name": "Hokko Tarumae",
            "text": "(But wait... My surroundings... Like putting a\nposter of Hokkaido sayings up in my room. Could\nthat help?)"
        },
        {
            "name": "Copano Rickey",
            "text": "Oh, are you interested? Ready to begin your feng\nshui journey? ☆"
        },
        {
            "name": "Hokko Tarumae",
            "text": "N-not one bit. I'm gonna change through good ol'\nhard work and perseverance!"
        }
    ]
}