{
    "title": "0",
    "no_wrap": true,
    "text_block_list": [
        {
            "name": "Oguri Cap",
            "text": "Hrm... The bell rang before I could finish my test\nagain."
        },
        {
            "name": "Oguri Cap",
            "text": "If I was a quick thinker like Tama, would my\nscores go up? Just like... Tama..."
        },
        {
            "name": "Oguri Cap",
            "text": "Whatcha talkin' 'bout?"
        },
        {
            "name": "Oguri Cap",
            "text": "Yup, that's her, all right."
        }
    ]
}