{
    "title": "秋華賞の後に・冠、掲げて",
    "no_wrap": true,
    "text_block_list": [
        {
            "name": "Monologue",
            "text": "Mejiro Dober carves her name into history after\ncompleting the Triple Tiara with an outstanding\nperformance!"
        },
        {
            "name": "Monologue",
            "text": "Though the audience's cheers threaten to move\nher to tears, Mejiro Dober presents herself in a\nrefined manner befitting a queen."
        },
        {
            "name": "Monologue",
            "text": "Afterward, Mejiro Dober thanks me again for\nbelieving in her, and the two of us take our first\nstep toward our new future!"
        }
    ]
}