{
    "title": "ポジティブ逃げネバギバ！",
    "no_wrap": true,
    "text_block_list": [
        {
            "text": "I spot Mejiro Palmer and some other runners\ntraining for a race."
        },
        {
            "name": "Mejiro Palmer",
            "text": "<i>Huff... Huff...</i> What a <i>workout!</i>"
        },
        {
            "name": "Mejiro Palmer",
            "text": "I shouldn't be so worn out doing this kinda thing\nthough. Especially since our next race is giving\nserious next-level vibes..."
        },
        {
            "name": "Daitaku Helios",
            "text": "That just means we're next level too! This race\n'bout to be a party for <i>real!</i>"
        },
        {
            "name": "Daitaku Helios",
            "text": "We gotta keep the party vibes going! We'll go\nhard with our runaway strat and light the stands\non fire!"
        },
        {
            "name": "Mejiro Palmer",
            "text": "Totally! We gotta get, uh... lit! Because we're next\nlevel!"
        },
        {
            "name": "Mejiro Palmer",
            "text": "Oh,I know! Wanna see if my freestyle racer\nfriends are up for a race? Running with them just\nhits different."
        },
        {
            "name": "Daitaku Helios",
            "text": "The freestyle racers?! Bet! That sounds fire!"
        },
        {
            "name": "Mejiro Palmer",
            "text": "Okay, let's get going then! ♪"
        },
        {
            "name": "Mejiro Palmer",
            "text": "Hey, you! You can come along too if you want!"
        },
        {
            "text": "Mejiro Palmer invites me just as their\nconversation piques my interest."
        },
        {
            "text": "I tag along out of a combination of curiosity and\nconcern, and when we arrive..."
        },
        {
            "name": "Mejiro Palmer",
            "text": "Hey, everyone! It's been aaages! You guys are\nlookin' great!"
        },
        {
            "name": "Umamusume A",
            "text": "Oh, Palmer! Look at that tracksuit... I guess that\nmeans you got in to Tracen Academy!"
        },
        {
            "name": "Daitaku Helios",
            "text": "Waheeeey! How's it goin', everybody?! Lemme\nhear ya scream!"
        },
        {
            "name": "Umamusume B",
            "text": "Woo, woo!"
        },
        {
            "name": "Umamusume A",
            "text": "Is this person with you too? Omigosh, you've got\na badge. Are you a trainer?!"
        },
        {
            "name": "Mejiro Palmer",
            "text": "Yeah, I kinda dragged 'em along."
        },
        {
            "text": "All the Umamusume here have their own reasons\nfor gathering here to run in this unofficial race."
        },
        {
            "name": "Umamusume A",
            "text": "So, what's the deal today?"
        },
        {
            "name": "Mejiro Palmer",
            "text": "We've got a race comin' up, so we're here to get\nthe vibes goin'."
        },
        {
            "name": "Umamusume A",
            "text": "So you wanna revisit the good old days, huh? Hell\nyeah! I'll help you out!"
        },
        {
            "name": "Umamusume B",
            "text": "Then I'll race you! Work's been stressing me out,\nso I'm ready to pop off!"
        },
        {
            "name": "Umamusume B",
            "text": "Plus, I wanna see what Tracen Academy's really\nmade of. I haven't given up on getting in yet!"
        },
        {
            "name": "Mejiro Palmer",
            "text": "Yeah! Let's do it!"
        },
        {
            "text": "The race is held on a quiet country road, but it's\nstill a sight to behold."
        },
        {
            "name": "Mejiro Palmer",
            "text": "Haha, we finished at the same time!"
        },
        {
            "name": "Umamusume A",
            "text": "Wow, you're the real deal, Palmer! You've really\nimproved! You too, Helios! I've never seen\nanyone blast to the front like that!"
        },
        {
            "name": "Daitaku Helios",
            "text": "Hehe, you guys were legit <i>on fire!</i> I knew I had to\ngo hard or go home!"
        },
        {
            "name": "Mejiro Palmer",
            "text": "This takes me back to my amateur days. I knew\ncoming here would make for a great escape!"
        },
        {
            "name": "Mejiro Palmer",
            "text": "You helped bring back my memories of this place\ntoday, Helios."
        },
        {
            "name": "Mejiro Palmer",
            "text": "It's like you're my sun or something! For real\nthough, thanks!"
        },
        {
            "name": "Daitaku Helios",
            "text": "Same, bestie! I made a ton of new friends and got\nto run a bunch! Today high-key slapped!",
            "choice_data_list": [
                "You two make a good duo.",
                "You two make a good duo.",
                "So for you, \"running away\" embodies your will\nto improve.",
                "So for you, \"running away\" embodies your will\nto improve."
            ]
        },
        {
            "name": "Daitaku Helios",
            "text": "Same, bestie! I made a ton of new friends and got\nto run a bunch! Today high-key slapped!",
            "choice_data_list": [
                "You two make a good duo.",
                "You two make a good duo.",
                "So for you, \"running away\" embodies your will\nto improve.",
                "So for you, \"running away\" embodies your will\nto improve."
            ]
        },
        {
            "name": "Mejiro Palmer",
            "text": "Uh-huh, we're a perfect pair! Let's have a blast at\nthe actual race too!"
        },
        {
            "name": "Daitaku Helios",
            "text": "Bet! And after this vibe check, we're gonna <i>serve</i>\non the racecourse! No cap!"
        },
        {
            "text": "On the day of the race, the perfect pair start the\nrace by seizing a huge lead..."
        },
        {
            "text": "Wooooo!"
        },
        {
            "name": "Daitaku Helios",
            "text": "(No way! Palmer's absolutely slaying! I can barely\nkeep up!)"
        },
        {
            "name": "Daitaku Helios",
            "text": "(But feel that fiery energy! She's giving off main\ncharacter vibes, like, <i>for real</i> !)"
        },
        {
            "name": "Daitaku Helios",
            "text": "GO FOR THE WIN! PAAAAALMERRRRR!"
        },
        {
            "name": "Mejiro Palmer",
            "text": "HAAAAAHHHHH!"
        },
        {
            "text": "Mejiro Palmer triumphantly takes first place, with\nDaitaku Helios right behind her!"
        },
        {
            "name": "Mejiro Palmer",
            "text": "Hahaha! AWESOME!"
        },
        {
            "name": "Daitaku Helios",
            "text": "Ahaha! Congrats!"
        },
        {
            "name": "Mejiro Palmer",
            "text": "Thanks, Bestie! That won't be the last time I make\na great escape!"
        },
        {
            "name": "Mejiro Palmer",
            "text": "Ack!"
        },
        {
            "name": "Daitaku Helios",
            "text": "Whoa?!"
        },
        {
            "text": "With only a little further to go, the two runners\nlose their steam and fail to keep ahead of the\npack before reaching the finish line."
        },
        {
            "name": "Mejiro Palmer",
            "text": "(We didn't make it! But... I feel like I saw the path\nto victory!)"
        },
        {
            "name": "Mejiro Palmer",
            "text": "(I don't care if people think I'm just some runaway\nfool, I'm not letting things end this way!)"
        },
        {
            "name": "Mejiro Palmer",
            "text": "I hate losing, but if I'm gonna be a fool, then I'm\ngonna be a fool to the end!"
        },
        {
            "text": "Mejiro Palmer stands on the track, eyes shining\nbright with intense determination."
        },
        {
            "name": "Mejiro Palmer",
            "text": "Yeah. I'm gonna run with all I've got. And when I\ndo, I'll see just how big the world really is."
        },
        {
            "name": "Umamusume A",
            "text": "We'll be there to cheer for you guys too, so break\na leg, Palmer and Helios!"
        },
        {
            "name": "Daitaku Helios",
            "text": "Ehehe, bet! Can't have an after-party without the\nwhole gang there!"
        },
        {
            "name": "Mejiro Palmer",
            "text": "You always get so ahead of yourself, Helios!\nAnyway, let's run away toward a future full of fun!"
        },
        {
            "text": "On the day of the race, the perfect pair start the\nrace by seizing a huge lead..."
        },
        {
            "text": "Wooooo!"
        },
        {
            "name": "Mejiro Palmer",
            "text": "YEEEEEAAAAAHHHHH!"
        },
        {
            "name": "Daitaku Helios",
            "text": "(For real?! That was a total serve, Palmer!)"
        },
        {
            "text": "That day, everyone gets to witness how a little\nescape can lead to big things."
        }
    ]
}