{
    "title": "有馬記念の後に・有馬の顔は……",
    "no_wrap": true,
    "text_block_list": [
        {
            "name": "Monologue",
            "text": "Having achieved her goal of overtaking Tokai\nTeio and winning the Arima Kinen, Nice Nature\nsheds tears of joy."
        },
        {
            "name": "Monologue",
            "text": "In the post-race press interview, a reporter asks\nNice Nature what led to her victory, and she\nanswers that it was because she gave the race her\nall."
        },
        {
            "name": "Monologue",
            "text": "She declares that she will never let her fans down\nso long as they continue to support her."
        },
        {
            "name": "Monologue",
            "text": "Nice Nature now radiates confidence, having\nbecome the shining main character in her own\nright."
        }
    ]
}